servicex_did_finder_lib/__init__.py
servicex_did_finder_lib/accumulator.py
servicex_did_finder_lib/communication.py
servicex_did_finder_lib/did_finder_app.py
servicex_did_finder_lib/did_logging.py
servicex_did_finder_lib/did_summary.py
servicex_did_finder_lib/exceptions.py
servicex_did_finder_lib/servicex_adaptor.py
servicex_did_finder_lib/util_uri.py
servicex_did_finder_lib-3.1.1.dist-info/LICENSE
servicex_did_finder_lib-3.1.1.dist-info/METADATA
servicex_did_finder_lib-3.1.1.dist-info/WHEEL
servicex_did_finder_lib-3.1.1.dist-info/RECORD
