Metadata-Version: 2.1
Name: ServiceX_DID_Finder_lib
Version: 3.1.1
Summary: ServiceX DID Library Routines
Author: Gordon Watts
Author-email: gwatts@uw.edu
Requires-Python: >=3.8.1,<4.0.0
Classifier: Programming Language :: Python :: 3
Classifier: Programming Language :: Python :: 3.9
Classifier: Programming Language :: Python :: 3.10
Classifier: Programming Language :: Python :: 3.11
Classifier: Programming Language :: Python :: 3.12
Classifier: Programming Language :: Python :: 3.13
Requires-Dist: Celery (>=5.4,<6.0)
Requires-Dist: make-it-sync (>=1.0.0,<2.0.0)
Requires-Dist: requests (>=2.25.0,<3.0.0)
